tshistory_refinery/__init__.py
tshistory_refinery/api.py
tshistory_refinery/blueprint.py
tshistory_refinery/cache.py
tshistory_refinery/cli.py
tshistory_refinery/funcs.py
tshistory_refinery/helper.py
tshistory_refinery/http.py
tshistory_refinery/migrate.py
tshistory_refinery/schema.py
tshistory_refinery/schema.sql
tshistory_refinery/scrap.py
tshistory_refinery/search.py
tshistory_refinery/tasks.py
tshistory_refinery/tsio.py
tshistory_refinery/webapp.py
tshistory_refinery/wsgi.py
tshistory_refinery/refinery_static/arrow.ico
tshistory_refinery/refinery_static/cockpit.css
tshistory_refinery/refinery_static/diagram.ico
tshistory_refinery/refinery_static/style.css
tshistory_refinery/templates/base.html
tshistory_refinery/templates/bigtable.html
tshistory_refinery/templates/formula_form.html
tshistory_refinery/templates/summary.html
tshistory_refinery-0.9.1.dist-info/LICENSE
tshistory_refinery-0.9.1.dist-info/METADATA
tshistory_refinery-0.9.1.dist-info/WHEEL
tshistory_refinery-0.9.1.dist-info/entry_points.txt
tshistory_refinery-0.9.1.dist-info/top_level.txt
tshistory_refinery-0.9.1.dist-info/RECORD
