Metadata-Version: 2.1
Name: tshistory_refinery
Version: 0.9.1
Author: Pythonian
Author-email: aurelien.campeas@pythonian.fr, arnaud.campeas@pythonian.fr
Classifier: Development Status :: 4 - Beta
Classifier: Intended Audience :: Developers
Classifier: License :: OSI Approved :: GNU Lesser General Public License v3 (LGPLv3)
Classifier: Operating System :: OS Independent
Classifier: Programming Language :: Python :: 3
Classifier: Topic :: Database
Classifier: Topic :: Scientific/Engineering
Classifier: Topic :: Software Development :: Version Control
Classifier: Topic :: Software Development :: Libraries :: Application Frameworks
License-File: LICENSE
Requires-Dist: dbcache>=0.5.0
Requires-Dist: tshistory>=0.20.1
Requires-Dist: tsview>=0.20.0
Requires-Dist: tshistory-supervision>=0.13.1
Requires-Dist: tshistory-formula>=0.16.2
Requires-Dist: tshistory-xl>=0.8.0
Requires-Dist: rework>=0.17.2
Requires-Dist: rework-ui>=0.16.0
Requires-Dist: inireader
Requires-Dist: pytest-sa-pg
Requires-Dist: webtest
Requires-Dist: responses
Requires-Dist: requests
Requires-Dist: pml
Requires-Dist: pygments
Requires-Dist: python-icron
Provides-Extra: doc
Requires-Dist: sphinx==4.5.0; extra == "doc"
Requires-Dist: sphinx-rtd-theme; extra == "doc"
Requires-Dist: sphinx-autoapi; extra == "doc"
Requires-Dist: pydata-sphinx-theme; extra == "doc"
